pipfixer/__init__.py
pipfixer/cli.py
pipfixer/core.py
pipfixer-1.0.4.dist-info/METADATA
pipfixer-1.0.4.dist-info/WHEEL
pipfixer-1.0.4.dist-info/entry_points.txt
pipfixer-1.0.4.dist-info/top_level.txt
pipfixer-1.0.4.dist-info/RECORD
