Metadata-Version: 2.4
Name: pipfixer
Version: 1.0.4
Summary: Auto-installs missing Python imports from a script
Author: PozStudio
Author-email: you@example.com
Requires-Python: >=3.6
Dynamic: author
Dynamic: author-email
Dynamic: description
Dynamic: description-content-type
Dynamic: requires-python
Dynamic: summary
